setup.py
django_googl.egg-info/PKG-INFO
django_googl.egg-info/SOURCES.txt
django_googl.egg-info/dependency_links.txt
django_googl.egg-info/top_level.txt
googl/__init__.py
googl/short.py
googl/templatetags/__init__.py
googl/templatetags/googlshort.py
googl/tests/__init__.py