Metadata-Version: 1.0
Name: django-googl
Version: 0.1.3
Summary: Django shorturl via goo.gl
Home-page: https://github.com/avelino/django-googl/
Author: Thiago Avelino
Author-email: thiagoavelinoster@gmail.com
License: BSD
Download-URL: https://github.com/avelino/django-googl/tarball/master
Keywords: django apps googl google api short url
Platform: UNKNOWN
Classifier: Environment :: Plugins
Classifier: Framework :: Django
Classifier: Intended Audience :: Developers
Classifier: License :: OSI Approved :: BSD License
Classifier: Operating System :: OS Independent
Classifier: Programming Language :: Python
Classifier: Topic :: Software Development :: Libraries :: Python Modules
